MANIFEST.in
README.rst
setup.py
bootstrap3_sass/__init__.py
bootstrap3_sass/admin.py
bootstrap3_sass/models.py
bootstrap3_sass/tests.py
bootstrap3_sass/views.py
bootstrap3_sass/static/.DS_Store
bootstrap3_sass/static/_bootstrap.scss
bootstrap3_sass/static/bootstrap/_alerts.scss
bootstrap3_sass/static/bootstrap/_badges.scss
bootstrap3_sass/static/bootstrap/_breadcrumbs.scss
bootstrap3_sass/static/bootstrap/_button-groups.scss
bootstrap3_sass/static/bootstrap/_buttons.scss
bootstrap3_sass/static/bootstrap/_carousel.scss
bootstrap3_sass/static/bootstrap/_close.scss
bootstrap3_sass/static/bootstrap/_code.scss
bootstrap3_sass/static/bootstrap/_component-animations.scss
bootstrap3_sass/static/bootstrap/_dropdowns.scss
bootstrap3_sass/static/bootstrap/_forms.scss
bootstrap3_sass/static/bootstrap/_glyphicons.scss
bootstrap3_sass/static/bootstrap/_grid.scss
bootstrap3_sass/static/bootstrap/_input-groups.scss
bootstrap3_sass/static/bootstrap/_jumbotron.scss
bootstrap3_sass/static/bootstrap/_labels.scss
bootstrap3_sass/static/bootstrap/_list-group.scss
bootstrap3_sass/static/bootstrap/_media.scss
bootstrap3_sass/static/bootstrap/_mixins.scss
bootstrap3_sass/static/bootstrap/_modals.scss
bootstrap3_sass/static/bootstrap/_navbar.scss
bootstrap3_sass/static/bootstrap/_navs.scss
bootstrap3_sass/static/bootstrap/_normalize.scss
bootstrap3_sass/static/bootstrap/_pager.scss
bootstrap3_sass/static/bootstrap/_pagination.scss
bootstrap3_sass/static/bootstrap/_panels.scss
bootstrap3_sass/static/bootstrap/_popovers.scss
bootstrap3_sass/static/bootstrap/_print.scss
bootstrap3_sass/static/bootstrap/_progress-bars.scss
bootstrap3_sass/static/bootstrap/_responsive-embed.scss
bootstrap3_sass/static/bootstrap/_responsive-utilities.scss
bootstrap3_sass/static/bootstrap/_scaffolding.scss
bootstrap3_sass/static/bootstrap/_tables.scss
bootstrap3_sass/static/bootstrap/_theme.scss
bootstrap3_sass/static/bootstrap/_thumbnails.scss
bootstrap3_sass/static/bootstrap/_tooltip.scss
django_bootstrap3_sass.egg-info/PKG-INFO
django_bootstrap3_sass.egg-info/SOURCES.txt
django_bootstrap3_sass.egg-info/dependency_links.txt
django_bootstrap3_sass.egg-info/requires.txt
django_bootstrap3_sass.egg-info/top_level.txt